IsarnConnect/DatabaseType.py
IsarnConnect/Meter.py
IsarnConnect/RowArray.py
IsarnConnect/__init__.py
IsarnConnect/isarn_connection.py
IsarnConnect/methods.py
IsarnConnect/db/ELS.py
IsarnConnect/db/LGZ.py
IsarnConnect/db/SLB.py
IsarnConnect/db/__init__.py
IsarnConnect/meters/Row.py
IsarnConnect/meters/__init__.py
isarnconnect-1.4.4.dist-info/METADATA
isarnconnect-1.4.4.dist-info/WHEEL
isarnconnect-1.4.4.dist-info/top_level.txt
isarnconnect-1.4.4.dist-info/RECORD
