Metadata-Version: 2.4
Name: IsarnConnect
Version: 1.4.4
Author: C0MaE
Author-email: jannis.koberg@icloud.com
Requires-Dist: psycopg2-binary>=2.9.9
Requires-Dist: sqlalchemy>=2.0.27
Requires-Dist: pandas>=2.2.1
Requires-Dist: mysql-connector-python>=2.2.9
Dynamic: author
Dynamic: author-email
Dynamic: description
Dynamic: description-content-type
Dynamic: requires-dist
